{
  "preprocess_config": {
    "process_width": 512,
    "process_height": 512,
    "preprocess_txt_action": "ignore",
    "process_flip": false,
    "process_split": false,
    "process_focal_crop": false,
    "process_multicrop": false,
    "process_caption": false,
    "process_caption_deepbooru": true
  },
  "train_param": {
    "pretrained_model_name_or_path": "runwayml/stable-diffusion-v1-5",
    "save_model_as": "safetensors",
    "v2": false,
    "v_parameterization": false,
    "output_name": "test",
    "training_comment": "test",
    "LoRA_type": "Standard",
    "lora_network_weights": "",
    "train_batch_size": 2,
    "epoch": "1",
    "save_every_n_epochs": "1",
    "caption_extension": ".txt",
    "mixed_precision": "fp16",
    "save_precision": "fp16",
    "num_cpu_threads_per_process": 2,
    "cache_latents": true,
    "seed": "1234",
    "learning_rate": "0.0001",
    "lr_scheduler": "constant",
    "lr_warmup": "0",
    "optimizer": "AdamW8bit",
    "optimizer_args": "",
    "text_encoder_lr": "5e-5",
    "unet_lr": "0.0001",
    "network_dim": 128,
    "network_alpha": 128,
    "conv_dim": 1,
    "conv_alpha": 1,
    "max_resolution": "512,512",
    "stop_text_encoder_training_pct": 0,
    "enable_bucket": false,
    "no_token_padding": false,
    "gradient_accumulation_steps": 1,
    "prior_loss_weight": 1,
    "lr_scheduler_num_cycles": "",
    "lr_scheduler_power": "",
    "additional_parameters": "",
    "keep_tokens": "0",
    "clip_skip": 2,
    "max_token_length": "75",
    "full_fp16": false,
    "gradient_checkpointing": false,
    "shuffle_caption": false,
    "persistent_data_loader_workers": false,
    "mem_eff_attn": false,
    "xformers": true,
    "color_aug": false,
    "flip_aug": false,
    "bucket_no_upscale": true,
    "bucket_reso_steps": 64,
    "random_crop": false,
    "noise_offset": "",
    "caption_dropout_every_n_epochs": 0,
    "caption_dropout_rate": 0,
    "vae_batch_size": 0,
    "max_train_epochs": "",
    "max_data_loader_n_workers": "1",
    "sample_every_n_steps": 0,
    "sample_every_n_epochs": 0,
    "sample_sampler": "euler_a",
    "sample_prompts": ""
  },
  "step": 100
}